jinjaform/__init__.py
jinjaform/__main__.py
jinjaform/aws.py
jinjaform/config.py
jinjaform/git.py
jinjaform/log.py
jinjaform/rc.py
jinjaform/terraform.py
jinjaform/workspace.py
jinjaform-0.5.4.dist-info/LICENSE
jinjaform-0.5.4.dist-info/METADATA
jinjaform-0.5.4.dist-info/WHEEL
jinjaform-0.5.4.dist-info/entry_points.txt
jinjaform-0.5.4.dist-info/top_level.txt
jinjaform-0.5.4.dist-info/RECORD
