Metadata-Version: 2.1
Name: jinjaform
Version: 0.5.4
Summary: Jinja2 Terraform wrapper
Home-page: https://github.com/claranet/jinjaform
Author: Raymond Butcher
Author-email: ray.butcher@claranet.uk
License: MIT License
Platform: UNKNOWN
Requires-Dist: boto-source-profile-mfa (>=0.0.4boto3)
Requires-Dist: botocore (>=1.8.14)
Requires-Dist: colorama
Requires-Dist: Jinja2
Requires-Dist: pyhcl
